{
  "width": 90,
  "height": 18,
  "commands": [
    {"op":"line","x1":12,"x2":17,"y":17,"ch":"."},
    {"op":"line","x1":34,"x2":37,"y":17,"ch":"."},
    {"op":"line","x1":58,"x2":61,"y":17,"ch":"."},
    {"op":"line","x1":78,"x2":81,"y":17,"ch":"."},

    {"op":"rect","x1":0,"y1":16,"x2":7,"y2":16,"ch":"#"},
    {"op":"rect","x1":18,"y1":16,"x2":25,"y2":16,"ch":"#"},
    {"op":"rect","x1":40,"y1":16,"x2":47,"y2":16,"ch":"#"},
    {"op":"rect","x1":64,"y1":16,"x2":71,"y2":16,"ch":"#"},
    {"op":"rect","x1":84,"y1":16,"x2":89,"y2":16,"ch":"#"},

    {"op":"line","x1":8,"x2":13,"y":12,"ch":"="},
    {"op":"line","x1":23,"x2":29,"y":11,"ch":"="},
    {"op":"line","x1":44,"x2":50,"y":10,"ch":"="},
    {"op":"line","x1":66,"x2":73,"y":9,"ch":"="},

    {"op":"many","ch":"S","items":[[3,16]]},
    {"op":"many","ch":"K","items":[[27,10],[69,8]]},
    {"op":"many","ch":"C","items":[[10,11],[24,10],[28,10],[45,9],[49,9],[67,8],[72,8],[86,15],[88,15],[20,15]]},
    {"op":"many","ch":"^","items":[[25,10],[46,9],[68,8],[86,15]]},
    {"op":"manyEnemies","items":[[20,16,"E"],[43,16,"E"],[66,16,"E"],[86,16,"E"]]}
  ]
}
